core_common_data_types/__init__.py
core_common_data_types/base_data_types.py
core_common_data_types/base_data_types_dtos.py
core_common_data_types/base_data_types_tos.py
core_common_data_types/py.typed
core_common_data_types/type_definitions.py
core_common_data_types/utils_data_types_tos.py
turintech_data_types-2.0.0.dist-info/METADATA
turintech_data_types-2.0.0.dist-info/WHEEL
turintech_data_types-2.0.0.dist-info/licenses/LICENSE
turintech_data_types-2.0.0.dist-info/RECORD
